ai_filesystem/__init__.py
ai_filesystem/client.py
ai_filesystem/exceptions.py
ai_filesystem/models.py
ai_filesystem/prompts.py
ai_filesystem-0.1.4.dist-info/licenses/LICENSE
ai_filesystem-0.1.4.dist-info/METADATA
ai_filesystem-0.1.4.dist-info/WHEEL
ai_filesystem-0.1.4.dist-info/top_level.txt
ai_filesystem-0.1.4.dist-info/RECORD
