Metadata-Version: 2.4
Name: ai-filesystem
Version: 0.1.4
Summary: Virtual filesystem service for AI agents with LangChain integration
Author-email: Nick <nick@langchain.dev>
License: MIT
Project-URL: Repository, https://github.com/langchain-ai/agent-file-system
Keywords: langchain,ai,filesystem,agents,tools
Classifier: Development Status :: 4 - Beta
Classifier: Intended Audience :: Developers
Classifier: License :: OSI Approved :: MIT License
Classifier: Programming Language :: Python :: 3
Classifier: Programming Language :: Python :: 3.11
Classifier: Programming Language :: Python :: 3.12
Classifier: Topic :: Software Development :: Libraries :: Python Modules
Classifier: Topic :: Scientific/Engineering :: Artificial Intelligence
Requires-Python: >=3.11
License-File: LICENSE
Requires-Dist: httpx>=0.25.2
Requires-Dist: pydantic>=2.5.0
Requires-Dist: langchain-core>=0.1.0
Requires-Dist: python-dotenv>=1.0.0
Provides-Extra: server
Requires-Dist: fastapi>=0.100.0; extra == "server"
Requires-Dist: uvicorn[standard]>=0.24.0; extra == "server"
Requires-Dist: asyncpg>=0.29.0; extra == "server"
Requires-Dist: python-jose[cryptography]>=3.3.0; extra == "server"
Requires-Dist: pydantic-settings>=2.10.1; extra == "server"
Requires-Dist: propelauth-fastapi>=4.2.8; extra == "server"
Dynamic: license-file
